
{
  "user": {
    "aUniqueUserID": {
      "name": "admin",
      "color": "red"
    }
  },
  "website": {
    "bonjour": {
      "channel": {
        "qna": [{
            "id": 0,
            "name": "fuzzbear77",
            "date": "12/11/2022",
            "comment": "This channel is empty...",
            "fire": 4,
            "color": "orange",
            "url": "",
            "channel": "Q&A"
        }]
      },
      "url": "https://en.wikipedia.org/wiki/Avatar:_The_Way_of_Water"
    }
  }
}
